gtfs_segments/__init__.py
gtfs_segments/geom_utils.py
gtfs_segments/gtfs_segments.py
gtfs_segments/mobility.py
gtfs_segments/partridge_func.py
gtfs_segments/route_stats.py
gtfs_segments/utils.py
gtfs_segments/partridge_mod/__init__.py
gtfs_segments/partridge_mod/__version__.py
gtfs_segments/partridge_mod/geo.py
gtfs_segments/partridge_mod/gtfs.py
gtfs_segments/partridge_mod/parsers.py
gtfs_segments/partridge_mod/readers.py
gtfs_segments/partridge_mod/utilities.py
gtfs_segments-2.1.7.dist-info/LICENSE
gtfs_segments-2.1.7.dist-info/METADATA
gtfs_segments-2.1.7.dist-info/WHEEL
gtfs_segments-2.1.7.dist-info/top_level.txt
gtfs_segments-2.1.7.dist-info/RECORD
