Metadata-Version: 2.1
Name: gtfs_segments
Version: 2.1.7
Summary: GTFS Segments: A fast and efficient library to generate bus stop spacings
Author-email: Saipraneeth Devunuri <sd37@illinois.edu>, Lewis Lehe <lehe@illinois.edu>
Maintainer-email: Saipraneeth Devunuri <sd37@illinois.edu>
License: MIT License
Project-URL: Homepage, https://github.com/UTEL-UIUC/gtfs_segments
Project-URL: Documentation, https://gtfs-segments.readthedocs.io
Project-URL: Repository, https://github.com/UTEL-UIUC/gtfs_segments
Project-URL: Bug Tracker, https://github.com/UTEL-UIUC/gtfs_segments/issues
Keywords: Python,GTFS,Transit,Stop Spacings,GIS
Classifier: Topic :: Software Development :: Libraries :: Python Modules
Classifier: Development Status :: 5 - Production/Stable
Classifier: License :: OSI Approved :: MIT License
Classifier: Programming Language :: Python :: 3.9
Classifier: Programming Language :: Python :: 3.10
Classifier: Programming Language :: Python :: 3.11
Classifier: Programming Language :: Python :: 3.9
Requires-Python: >=3.9
License-File: LICENSE
Requires-Dist: geopandas
Requires-Dist: scipy
Requires-Dist: shapely
Requires-Dist: numpy
Requires-Dist: pandas
Requires-Dist: matplotlib
Requires-Dist: utm
Requires-Dist: contextily
Requires-Dist: requests
Requires-Dist: isoweek
Requires-Dist: faust-cchardet
Requires-Dist: charset-normalizer
Requires-Dist: folium
Requires-Dist: thefuzz
